[
  {
    "line": 1,
    "elements": [
      {
        "start_timestamp": "2021-03-15T15:05:13.005Z",
        "before": [
          {
            "result": {
              "duration": 1857124231,
              "status": "passed"
            },
            "match": {
              "location": "Hooks.setUp()"
            }
          }
        ],
        "line": 12,
        "name": "User checks login functionality with valid credentials",
        "description": "",
        "id": "testing-login-functionality;user-checks-login-functionality-with-valid-credentials;;2",
        "after": [
          {
            "result": {
              "duration": 81180057,
              "status": "passed"
            },
            "match": {
              "location": "Hooks.tearDown(Scenario)"
            }
          }
        ],
        "type": "scenario",
        "keyword": "Scenario Outline",
        "steps": [
          {
            "result": {
              "duration": 618325910,
              "status": "passed"
            },
            "line": 5,
            "name": "user is on login page",
            "match": {
              "location": "LoginSteps.user_is_on_login_page()"
            },
            "keyword": "Given "
          },
          {
            "result": {
              "duration": 4155871469,
              "status": "passed"
            },
            "line": 6,
            "name": "user enters Hakan and 12345",
            "match": {
              "arguments": [
                {
                  "val": "Hakan",
                  "offset": 12
                },
                {
                  "val": "12345",
                  "offset": 22
                }
              ],
              "location": "LoginSteps.userEntersUsernameAndPasswords(String,String)"
            },
            "keyword": "When "
          },
          {
            "result": {
              "duration": 2058989552,
              "status": "passed"
            },
            "line": 7,
            "name": "user clicks on login button",
            "match": {
              "location": "LoginSteps.user_clicks_on_login_button()"
            },
            "keyword": "And "
          },
          {
            "result": {
              "duration": 2039166850,
              "status": "passed"
            },
            "line": 8,
            "name": "user is navigated to the home page",
            "match": {
              "location": "LoginSteps.user_is_navigated_to_the_home_page()"
            },
            "keyword": "Then "
          }
        ],
        "tags": [
          {
            "name": "@smoke"
          }
        ]
      },
      {
        "start_timestamp": "2021-03-15T15:05:23.853Z",
        "before": [
          {
            "result": {
              "duration": 1129690651,
              "status": "passed"
            },
            "match": {
              "location": "Hooks.setUp()"
            }
          }
        ],
        "line": 13,
        "name": "User checks login functionality with valid credentials",
        "description": "",
        "id": "testing-login-functionality;user-checks-login-functionality-with-valid-credentials;;3",
        "after": [
          {
            "result": {
              "duration": 82033356,
              "status": "passed"
            },
            "match": {
              "location": "Hooks.tearDown(Scenario)"
            }
          }
        ],
        "type": "scenario",
        "keyword": "Scenario Outline",
        "steps": [
          {
            "result": {
              "duration": 475021899,
              "status": "passed"
            },
            "line": 5,
            "name": "user is on login page",
            "match": {
              "location": "LoginSteps.user_is_on_login_page()"
            },
            "keyword": "Given "
          },
          {
            "result": {
              "duration": 4169135967,
              "status": "passed"
            },
            "line": 6,
            "name": "user enters Hasan and 12345",
            "match": {
              "arguments": [
                {
                  "val": "Hasan",
                  "offset": 12
                },
                {
                  "val": "12345",
                  "offset": 22
                }
              ],
              "location": "LoginSteps.userEntersUsernameAndPasswords(String,String)"
            },
            "keyword": "When "
          },
          {
            "result": {
              "duration": 2063809010,
              "status": "passed"
            },
            "line": 7,
            "name": "user clicks on login button",
            "match": {
              "location": "LoginSteps.user_clicks_on_login_button()"
            },
            "keyword": "And "
          },
          {
            "result": {
              "duration": 2034882288,
              "status": "passed"
            },
            "line": 8,
            "name": "user is navigated to the home page",
            "match": {
              "location": "LoginSteps.user_is_navigated_to_the_home_page()"
            },
            "keyword": "Then "
          }
        ],
        "tags": [
          {
            "name": "@smoke"
          }
        ]
      }
    ],
    "name": "testing login functionality",
    "description": "",
    "id": "testing-login-functionality",
    "keyword": "Feature",
    "uri": "file:src/test/resources/features/login.feature",
    "tags": []
  }
]